{
    "##": "This package is for private use only. Requires password for installation to proceed.",
    "version": "16.0.13929.20238",
    "description": "Microsoft Office 2019 (Chinese Trad.) (install all components: Word, Excel, Powerpoint, OneNote, Publisher, Access, Outlook, Skype for Business)",
    "license": "Proprietary",
    "url": "https://www.googleapis.com/drive/v3/files/11aojV7UyKkRgLA6G0gzQWjk2QNG-u7bM?alt=media&key=AIzaSyAiaA0bWx34SyfTRvyl4UCCHwsCkvUBECc#/dl.7z_",
    "hash": "801C38787CB8A4A445994588A6B3BB04AF08820A6EA843C6C9B72E0EC9A98F39",
    "installer": {
        "script": [
            "$scriptdir = (Find-BucketDirectory $bucket)+'\\..\\scripts'",
            "Import-Module $scriptdir\\pw\\pw_check.psm1",
            "$key = Get-Key",
            "if (!($key)) {",
            "   Write-Host 'Password incorrect -- abort installation' -ForegroundColor Red",
            "   break;",
            "}",
            "Write-Host 'Password is correct' -ForegroundColor Green",
            "New-Item \"$dir\\setup\" -ItemType Directory | Out-Null",
            "Invoke-ExternalCommand 7z -ArgumentList @('x', '-bso0', \"-o$dir\\setup\", \"-p$key\", \"$dir\\dl.7z_\") | Out-Null",
            "Invoke-ExternalCommand \"$dir\\setup\\setup.exe\" -ArgumentList @('/configure', \"$scriptdir\\office19\\full.xml\") -RunAs | Out-Null",
            "Remove-Item \"$dir\\dl.7z_\", \"$dir\\setup\" -Force -Recurse"
        ]
    },
    "uninstaller": {
        "script": [
            "Invoke-ExternalCommand \"$env:CommonProgramFiles\\microsoft shared\\ClickToRun\\OfficeClickToRun.exe\" -ArgumentList @('scenario=Install', 'scenariosubtype=Uninstall', 'productstoremove=ProPlus2019Volume_zh-tw_x-none', 'DisplayLevel=False') -RunAs | Out-Null",
            "while (Get-Process -Name OfficeClickToRun -ErrorAction SilentlyContinue) {",
            "    Start-Sleep -Seconds 1",
            "}"
        ]
    }
}
